dwd_downloader/__init__.py
dwd_downloader/api.py
dwd_downloader/cli.py
dwd_downloader/config.py
dwd_downloader/datasets.py
dwd_downloader/file_utils.py
dwd_downloader/html_utils.py
dwd_downloader/logger.py
dwd_downloader/mirror.py
dwd_downloader/storage.py
dwd_downloader/utils.py
dwd_downloader-1.0.7.dist-info/METADATA
dwd_downloader-1.0.7.dist-info/WHEEL
dwd_downloader-1.0.7.dist-info/entry_points.txt
dwd_downloader-1.0.7.dist-info/licenses/LICENSE
dwd_downloader-1.0.7.dist-info/RECORD
