Metadata-Version: 2.4
Name: dwd-downloader
Version: 1.0.7
Summary: Add your description here
License-File: LICENSE
Requires-Python: >=3.11
Requires-Dist: beautifulsoup4>=4.14.2
Requires-Dist: boto3>=1.40.66
Requires-Dist: fsspec>=2025.10.0
Requires-Dist: python-dotenv>=1.1.1
Requires-Dist: pyyaml>=6.0.3
Requires-Dist: requests>=2.32.5
